README.md
setup.cfg
setup.py
lp_stripe/__init__.py
lp_stripe/admin.py
lp_stripe/apps.py
lp_stripe/client.py
lp_stripe/conf.py
lp_stripe/models.py
lp_stripe/serializers.py
lp_stripe/test_rest.py
lp_stripe/tests.py
lp_stripe/urls.py
lp_stripe/views.py
lp_stripe.egg-info/PKG-INFO
lp_stripe.egg-info/SOURCES.txt
lp_stripe.egg-info/dependency_links.txt
lp_stripe.egg-info/top_level.txt
lp_stripe/fixtures/lp_stripe_users.json
lp_stripe/migrations/0001_initial.py
lp_stripe/migrations/0002_auto_20170905_1802.py
lp_stripe/migrations/0003_auto_20170905_2254.py
lp_stripe/migrations/__init__.py
lp_stripe/migrations/__pycache__