Metadata-Version: 1.1
Name: lp-stripe
Version: 0.1.7
Summary: REST Framework Stripe Payments
Home-page: https://github.com/Launchpeer/django-rest-stripe
Author: Jim Simon
Author-email: hello@launchpeer.com
License: UNKNOWN
Download-URL: https://github.com/Launchpeer/django-rest-stripe/archive/master.tar.gz
Platform: UNKNOWN
